<annotation>
	<folder>images</folder>
	<filename>brightnessimage002.jpg</filename>
	<path>D:\code\barcode-qrcode-images\images\brightnessimage002.jpg</path>
	<source>
		<database>Unknown</database>
	</source>
	<size>
		<width>3024</width>
		<height>4032</height>
		<depth>3</depth>
	</size>
	<segmented>0</segmented>
	<object>
		<name>QR_CODE</name>
		<pose>Unspecified</pose>
		<truncated>0</truncated>
		<difficult>0</difficult>
		<bndbox>
			<xmin>1976</xmin>
			<ymin>1699</ymin>
			<xmax>2468</xmax>
			<ymax>2186</ymax>
		</bndbox>
	</object>
	<object>
		<name>QR_CODE</name>
		<pose>Unspecified</pose>
		<truncated>0</truncated>
		<difficult>0</difficult>
		<bndbox>
			<xmin>1772</xmin>
			<ymin>2390</ymin>
			<xmax>2276</xmax>
			<ymax>2924</ymax>
		</bndbox>
	</object>
	<object>
		<name>QR_CODE</name>
		<pose>Unspecified</pose>
		<truncated>0</truncated>
		<difficult>0</difficult>
		<bndbox>
			<xmin>568</xmin>
			<ymin>1657</ymin>
			<xmax>1422</xmax>
			<ymax>2540</ymax>
		</bndbox>
	</object>
</annotation>
