<annotation>
	<folder>images</folder>
	<filename>lotsimage002.jpg</filename>
	<path>D:\code\barcode-qrcode-images\images\lotsimage002.jpg</path>
	<source>
		<database>Unknown</database>
	</source>
	<size>
		<width>3024</width>
		<height>4032</height>
		<depth>3</depth>
	</size>
	<segmented>0</segmented>
	<object>
		<name>QR_CODE</name>
		<pose>Unspecified</pose>
		<truncated>0</truncated>
		<difficult>0</difficult>
		<bndbox>
			<xmin>449</xmin>
			<ymin>444</ymin>
			<xmax>699</xmax>
			<ymax>728</ymax>
		</bndbox>
	</object>
	<object>
		<name>QR_CODE</name>
		<pose>Unspecified</pose>
		<truncated>0</truncated>
		<difficult>0</difficult>
		<bndbox>
			<xmin>724</xmin>
			<ymin>524</ymin>
			<xmax>974</xmax>
			<ymax>799</ymax>
		</bndbox>
	</object>
	<object>
		<name>QR_CODE</name>
		<pose>Unspecified</pose>
		<truncated>0</truncated>
		<difficult>0</difficult>
		<bndbox>
			<xmin>991</xmin>
			<ymin>586</ymin>
			<xmax>1254</xmax>
			<ymax>836</ymax>
		</bndbox>
	</object>
	<object>
		<name>QR_CODE</name>
		<pose>Unspecified</pose>
		<truncated>0</truncated>
		<difficult>0</difficult>
		<bndbox>
			<xmin>1270</xmin>
			<ymin>632</ymin>
			<xmax>1537</xmax>
			<ymax>890</ymax>
		</bndbox>
	</object>
	<object>
		<name>QR_CODE</name>
		<pose>Unspecified</pose>
		<truncated>0</truncated>
		<difficult>0</difficult>
		<bndbox>
			<xmin>399</xmin>
			<ymin>757</ymin>
			<xmax>645</xmax>
			<ymax>1007</ymax>
		</bndbox>
	</object>
	<object>
		<name>QR_CODE</name>
		<pose>Unspecified</pose>
		<truncated>0</truncated>
		<difficult>0</difficult>
		<bndbox>
			<xmin>674</xmin>
			<ymin>824</ymin>
			<xmax>904</xmax>
			<ymax>1053</ymax>
		</bndbox>
	</object>
	<object>
		<name>QR_CODE</name>
		<pose>Unspecified</pose>
		<truncated>0</truncated>
		<difficult>0</difficult>
		<bndbox>
			<xmin>945</xmin>
			<ymin>878</ymin>
			<xmax>1191</xmax>
			<ymax>1103</ymax>
		</bndbox>
	</object>
	<object>
		<name>QR_CODE</name>
		<pose>Unspecified</pose>
		<truncated>0</truncated>
		<difficult>0</difficult>
		<bndbox>
			<xmin>1220</xmin>
			<ymin>919</ymin>
			<xmax>1474</xmax>
			<ymax>1165</ymax>
		</bndbox>
	</object>
	<object>
		<name>QR_CODE</name>
		<pose>Unspecified</pose>
		<truncated>0</truncated>
		<difficult>0</difficult>
		<bndbox>
			<xmin>329</xmin>
			<ymin>1040</ymin>
			<xmax>595</xmax>
			<ymax>1274</ymax>
		</bndbox>
	</object>
	<object>
		<name>QR_CODE</name>
		<pose>Unspecified</pose>
		<truncated>0</truncated>
		<difficult>0</difficult>
		<bndbox>
			<xmin>629</xmin>
			<ymin>1103</ymin>
			<xmax>849</xmax>
			<ymax>1336</ymax>
		</bndbox>
	</object>
	<object>
		<name>QR_CODE</name>
		<pose>Unspecified</pose>
		<truncated>0</truncated>
		<difficult>0</difficult>
		<bndbox>
			<xmin>887</xmin>
			<ymin>1140</ymin>
			<xmax>1137</xmax>
			<ymax>1394</ymax>
		</bndbox>
	</object>
	<object>
		<name>QR_CODE</name>
		<pose>Unspecified</pose>
		<truncated>0</truncated>
		<difficult>0</difficult>
		<bndbox>
			<xmin>1170</xmin>
			<ymin>1211</ymin>
			<xmax>1429</xmax>
			<ymax>1449</ymax>
		</bndbox>
	</object>
	<object>
		<name>QR_CODE</name>
		<pose>Unspecified</pose>
		<truncated>0</truncated>
		<difficult>0</difficult>
		<bndbox>
			<xmin>299</xmin>
			<ymin>1307</ymin>
			<xmax>529</xmax>
			<ymax>1561</ymax>
		</bndbox>
	</object>
	<object>
		<name>QR_CODE</name>
		<pose>Unspecified</pose>
		<truncated>0</truncated>
		<difficult>0</difficult>
		<bndbox>
			<xmin>562</xmin>
			<ymin>1369</ymin>
			<xmax>804</xmax>
			<ymax>1607</ymax>
		</bndbox>
	</object>
	<object>
		<name>QR_CODE</name>
		<pose>Unspecified</pose>
		<truncated>0</truncated>
		<difficult>0</difficult>
		<bndbox>
			<xmin>837</xmin>
			<ymin>1424</ymin>
			<xmax>1070</xmax>
			<ymax>1665</ymax>
		</bndbox>
	</object>
	<object>
		<name>QR_CODE</name>
		<pose>Unspecified</pose>
		<truncated>0</truncated>
		<difficult>0</difficult>
		<bndbox>
			<xmin>1104</xmin>
			<ymin>1482</ymin>
			<xmax>1354</xmax>
			<ymax>1719</ymax>
		</bndbox>
	</object>
	<object>
		<name>QR_CODE</name>
		<pose>Unspecified</pose>
		<truncated>0</truncated>
		<difficult>0</difficult>
		<bndbox>
			<xmin>233</xmin>
			<ymin>1594</ymin>
			<xmax>483</xmax>
			<ymax>1828</ymax>
		</bndbox>
	</object>
	<object>
		<name>QR_CODE</name>
		<pose>Unspecified</pose>
		<truncated>0</truncated>
		<difficult>0</difficult>
		<bndbox>
			<xmin>508</xmin>
			<ymin>1649</ymin>
			<xmax>745</xmax>
			<ymax>1874</ymax>
		</bndbox>
	</object>
	<object>
		<name>QR_CODE</name>
		<pose>Unspecified</pose>
		<truncated>0</truncated>
		<difficult>0</difficult>
		<bndbox>
			<xmin>783</xmin>
			<ymin>1703</ymin>
			<xmax>1008</xmax>
			<ymax>1932</ymax>
		</bndbox>
	</object>
	<object>
		<name>QR_CODE</name>
		<pose>Unspecified</pose>
		<truncated>0</truncated>
		<difficult>0</difficult>
		<bndbox>
			<xmin>1070</xmin>
			<ymin>1761</ymin>
			<xmax>1291</xmax>
			<ymax>2007</ymax>
		</bndbox>
	</object>
	<object>
		<name>QR_CODE</name>
		<pose>Unspecified</pose>
		<truncated>0</truncated>
		<difficult>0</difficult>
		<bndbox>
			<xmin>1962</xmin>
			<ymin>807</ymin>
			<xmax>2212</xmax>
			<ymax>1074</ymax>
		</bndbox>
	</object>
	<object>
		<name>QR_CODE</name>
		<pose>Unspecified</pose>
		<truncated>0</truncated>
		<difficult>0</difficult>
		<bndbox>
			<xmin>2208</xmin>
			<ymin>949</ymin>
			<xmax>2470</xmax>
			<ymax>1199</ymax>
		</bndbox>
	</object>
	<object>
		<name>QR_CODE</name>
		<pose>Unspecified</pose>
		<truncated>0</truncated>
		<difficult>0</difficult>
		<bndbox>
			<xmin>2466</xmin>
			<ymin>1053</ymin>
			<xmax>2720</xmax>
			<ymax>1332</ymax>
		</bndbox>
	</object>
	<object>
		<name>QR_CODE</name>
		<pose>Unspecified</pose>
		<truncated>0</truncated>
		<difficult>0</difficult>
		<bndbox>
			<xmin>2724</xmin>
			<ymin>1178</ymin>
			<xmax>2987</xmax>
			<ymax>1457</ymax>
		</bndbox>
	</object>
	<object>
		<name>QR_CODE</name>
		<pose>Unspecified</pose>
		<truncated>0</truncated>
		<difficult>0</difficult>
		<bndbox>
			<xmin>1820</xmin>
			<ymin>1061</ymin>
			<xmax>2091</xmax>
			<ymax>1324</ymax>
		</bndbox>
	</object>
	<object>
		<name>QR_CODE</name>
		<pose>Unspecified</pose>
		<truncated>0</truncated>
		<difficult>0</difficult>
		<bndbox>
			<xmin>2079</xmin>
			<ymin>1203</ymin>
			<xmax>2354</xmax>
			<ymax>1449</ymax>
		</bndbox>
	</object>
	<object>
		<name>QR_CODE</name>
		<pose>Unspecified</pose>
		<truncated>0</truncated>
		<difficult>0</difficult>
		<bndbox>
			<xmin>2341</xmin>
			<ymin>1324</ymin>
			<xmax>2595</xmax>
			<ymax>1578</ymax>
		</bndbox>
	</object>
	<object>
		<name>QR_CODE</name>
		<pose>Unspecified</pose>
		<truncated>0</truncated>
		<difficult>0</difficult>
		<bndbox>
			<xmin>2595</xmin>
			<ymin>1449</ymin>
			<xmax>2874</xmax>
			<ymax>1715</ymax>
		</bndbox>
	</object>
	<object>
		<name>QR_CODE</name>
		<pose>Unspecified</pose>
		<truncated>0</truncated>
		<difficult>0</difficult>
		<bndbox>
			<xmin>1691</xmin>
			<ymin>1328</ymin>
			<xmax>1954</xmax>
			<ymax>1586</ymax>
		</bndbox>
	</object>
	<object>
		<name>QR_CODE</name>
		<pose>Unspecified</pose>
		<truncated>0</truncated>
		<difficult>0</difficult>
		<bndbox>
			<xmin>1954</xmin>
			<ymin>1449</ymin>
			<xmax>2212</xmax>
			<ymax>1703</ymax>
		</bndbox>
	</object>
	<object>
		<name>QR_CODE</name>
		<pose>Unspecified</pose>
		<truncated>0</truncated>
		<difficult>0</difficult>
		<bndbox>
			<xmin>2212</xmin>
			<ymin>1582</ymin>
			<xmax>2462</xmax>
			<ymax>1832</ymax>
		</bndbox>
	</object>
	<object>
		<name>QR_CODE</name>
		<pose>Unspecified</pose>
		<truncated>0</truncated>
		<difficult>0</difficult>
		<bndbox>
			<xmin>2470</xmin>
			<ymin>1711</ymin>
			<xmax>2729</xmax>
			<ymax>1965</ymax>
		</bndbox>
	</object>
	<object>
		<name>QR_CODE</name>
		<pose>Unspecified</pose>
		<truncated>0</truncated>
		<difficult>0</difficult>
		<bndbox>
			<xmin>1570</xmin>
			<ymin>1578</ymin>
			<xmax>1833</xmax>
			<ymax>1836</ymax>
		</bndbox>
	</object>
	<object>
		<name>QR_CODE</name>
		<pose>Unspecified</pose>
		<truncated>0</truncated>
		<difficult>0</difficult>
		<bndbox>
			<xmin>1829</xmin>
			<ymin>1694</ymin>
			<xmax>2079</xmax>
			<ymax>1961</ymax>
		</bndbox>
	</object>
	<object>
		<name>QR_CODE</name>
		<pose>Unspecified</pose>
		<truncated>0</truncated>
		<difficult>0</difficult>
		<bndbox>
			<xmin>2079</xmin>
			<ymin>1828</ymin>
			<xmax>2333</xmax>
			<ymax>2090</ymax>
		</bndbox>
	</object>
	<object>
		<name>QR_CODE</name>
		<pose>Unspecified</pose>
		<truncated>0</truncated>
		<difficult>0</difficult>
		<bndbox>
			<xmin>2329</xmin>
			<ymin>1953</ymin>
			<xmax>2599</xmax>
			<ymax>2211</ymax>
		</bndbox>
	</object>
	<object>
		<name>QR_CODE</name>
		<pose>Unspecified</pose>
		<truncated>0</truncated>
		<difficult>0</difficult>
		<bndbox>
			<xmin>1437</xmin>
			<ymin>1819</ymin>
			<xmax>1695</xmax>
			<ymax>2082</ymax>
		</bndbox>
	</object>
	<object>
		<name>QR_CODE</name>
		<pose>Unspecified</pose>
		<truncated>0</truncated>
		<difficult>0</difficult>
		<bndbox>
			<xmin>1704</xmin>
			<ymin>1961</ymin>
			<xmax>1941</xmax>
			<ymax>2219</ymax>
		</bndbox>
	</object>
	<object>
		<name>QR_CODE</name>
		<pose>Unspecified</pose>
		<truncated>0</truncated>
		<difficult>0</difficult>
		<bndbox>
			<xmin>1949</xmin>
			<ymin>2094</ymin>
			<xmax>2199</xmax>
			<ymax>2332</ymax>
		</bndbox>
	</object>
	<object>
		<name>QR_CODE</name>
		<pose>Unspecified</pose>
		<truncated>0</truncated>
		<difficult>0</difficult>
		<bndbox>
			<xmin>2204</xmin>
			<ymin>2211</ymin>
			<xmax>2470</xmax>
			<ymax>2478</ymax>
		</bndbox>
	</object>
	<object>
		<name>QR_CODE</name>
		<pose>Unspecified</pose>
		<truncated>0</truncated>
		<difficult>0</difficult>
		<bndbox>
			<xmin>899</xmin>
			<ymin>2140</ymin>
			<xmax>1145</xmax>
			<ymax>2403</ymax>
		</bndbox>
	</object>
	<object>
		<name>QR_CODE</name>
		<pose>Unspecified</pose>
		<truncated>0</truncated>
		<difficult>0</difficult>
		<bndbox>
			<xmin>1066</xmin>
			<ymin>2365</ymin>
			<xmax>1320</xmax>
			<ymax>2619</ymax>
		</bndbox>
	</object>
	<object>
		<name>QR_CODE</name>
		<pose>Unspecified</pose>
		<truncated>0</truncated>
		<difficult>0</difficult>
		<bndbox>
			<xmin>1241</xmin>
			<ymin>2574</ymin>
			<xmax>1495</xmax>
			<ymax>2828</ymax>
		</bndbox>
	</object>
	<object>
		<name>QR_CODE</name>
		<pose>Unspecified</pose>
		<truncated>0</truncated>
		<difficult>0</difficult>
		<bndbox>
			<xmin>1416</xmin>
			<ymin>2794</ymin>
			<xmax>1679</xmax>
			<ymax>3057</ymax>
		</bndbox>
	</object>
	<object>
		<name>QR_CODE</name>
		<pose>Unspecified</pose>
		<truncated>0</truncated>
		<difficult>0</difficult>
		<bndbox>
			<xmin>1604</xmin>
			<ymin>3015</ymin>
			<xmax>1866</xmax>
			<ymax>3274</ymax>
		</bndbox>
	</object>
	<object>
		<name>QR_CODE</name>
		<pose>Unspecified</pose>
		<truncated>0</truncated>
		<difficult>0</difficult>
		<bndbox>
			<xmin>670</xmin>
			<ymin>2299</ymin>
			<xmax>933</xmax>
			<ymax>2574</ymax>
		</bndbox>
	</object>
	<object>
		<name>QR_CODE</name>
		<pose>Unspecified</pose>
		<truncated>0</truncated>
		<difficult>0</difficult>
		<bndbox>
			<xmin>854</xmin>
			<ymin>2540</ymin>
			<xmax>1112</xmax>
			<ymax>2799</ymax>
		</bndbox>
	</object>
	<object>
		<name>QR_CODE</name>
		<pose>Unspecified</pose>
		<truncated>0</truncated>
		<difficult>0</difficult>
		<bndbox>
			<xmin>1037</xmin>
			<ymin>2744</ymin>
			<xmax>1291</xmax>
			<ymax>3007</ymax>
		</bndbox>
	</object>
	<object>
		<name>QR_CODE</name>
		<pose>Unspecified</pose>
		<truncated>0</truncated>
		<difficult>0</difficult>
		<bndbox>
			<xmin>1208</xmin>
			<ymin>2961</ymin>
			<xmax>1470</xmax>
			<ymax>3228</ymax>
		</bndbox>
	</object>
	<object>
		<name>QR_CODE</name>
		<pose>Unspecified</pose>
		<truncated>0</truncated>
		<difficult>0</difficult>
		<bndbox>
			<xmin>1395</xmin>
			<ymin>3190</ymin>
			<xmax>1662</xmax>
			<ymax>3453</ymax>
		</bndbox>
	</object>
	<object>
		<name>QR_CODE</name>
		<pose>Unspecified</pose>
		<truncated>0</truncated>
		<difficult>0</difficult>
		<bndbox>
			<xmin>454</xmin>
			<ymin>2478</ymin>
			<xmax>720</xmax>
			<ymax>2753</ymax>
		</bndbox>
	</object>
	<object>
		<name>QR_CODE</name>
		<pose>Unspecified</pose>
		<truncated>0</truncated>
		<difficult>0</difficult>
		<bndbox>
			<xmin>645</xmin>
			<ymin>2711</ymin>
			<xmax>899</xmax>
			<ymax>2969</ymax>
		</bndbox>
	</object>
	<object>
		<name>QR_CODE</name>
		<pose>Unspecified</pose>
		<truncated>0</truncated>
		<difficult>0</difficult>
		<bndbox>
			<xmin>812</xmin>
			<ymin>2928</ymin>
			<xmax>1070</xmax>
			<ymax>3178</ymax>
		</bndbox>
	</object>
	<object>
		<name>QR_CODE</name>
		<pose>Unspecified</pose>
		<truncated>0</truncated>
		<difficult>0</difficult>
		<bndbox>
			<xmin>991</xmin>
			<ymin>3144</ymin>
			<xmax>1249</xmax>
			<ymax>3399</ymax>
		</bndbox>
	</object>
	<object>
		<name>QR_CODE</name>
		<pose>Unspecified</pose>
		<truncated>0</truncated>
		<difficult>0</difficult>
		<bndbox>
			<xmin>1170</xmin>
			<ymin>3361</ymin>
			<xmax>1437</xmax>
			<ymax>3615</ymax>
		</bndbox>
	</object>
	<object>
		<name>QR_CODE</name>
		<pose>Unspecified</pose>
		<truncated>0</truncated>
		<difficult>0</difficult>
		<bndbox>
			<xmin>249</xmin>
			<ymin>2669</ymin>
			<xmax>516</xmax>
			<ymax>2924</ymax>
		</bndbox>
	</object>
	<object>
		<name>QR_CODE</name>
		<pose>Unspecified</pose>
		<truncated>0</truncated>
		<difficult>0</difficult>
		<bndbox>
			<xmin>429</xmin>
			<ymin>2869</ymin>
			<xmax>683</xmax>
			<ymax>3149</ymax>
		</bndbox>
	</object>
	<object>
		<name>QR_CODE</name>
		<pose>Unspecified</pose>
		<truncated>0</truncated>
		<difficult>0</difficult>
		<bndbox>
			<xmin>599</xmin>
			<ymin>3103</ymin>
			<xmax>862</xmax>
			<ymax>3357</ymax>
		</bndbox>
	</object>
	<object>
		<name>QR_CODE</name>
		<pose>Unspecified</pose>
		<truncated>0</truncated>
		<difficult>0</difficult>
		<bndbox>
			<xmin>783</xmin>
			<ymin>3324</ymin>
			<xmax>1045</xmax>
			<ymax>3578</ymax>
		</bndbox>
	</object>
	<object>
		<name>QR_CODE</name>
		<pose>Unspecified</pose>
		<truncated>0</truncated>
		<difficult>0</difficult>
		<bndbox>
			<xmin>966</xmin>
			<ymin>3532</ymin>
			<xmax>1220</xmax>
			<ymax>3803</ymax>
		</bndbox>
	</object>
</annotation>
