<annotation>
	<folder>images</folder>
	<filename>noncompliantimage002.jpg</filename>
	<path>D:\code\barcode-qrcode-images\images\noncompliantimage002.jpg</path>
	<source>
		<database>Unknown</database>
	</source>
	<size>
		<width>2013</width>
		<height>1425</height>
		<depth>3</depth>
	</size>
	<segmented>0</segmented>
	<object>
		<name>QR_CODE</name>
		<pose>Unspecified</pose>
		<truncated>0</truncated>
		<difficult>0</difficult>
		<bndbox>
			<xmin>226</xmin>
			<ymin>484</ymin>
			<xmax>990</xmax>
			<ymax>1310</ymax>
		</bndbox>
	</object>
	<object>
		<name>QR_CODE</name>
		<pose>Unspecified</pose>
		<truncated>0</truncated>
		<difficult>0</difficult>
		<bndbox>
			<xmin>1003</xmin>
			<ymin>128</ymin>
			<xmax>1695</xmax>
			<ymax>829</ymax>
		</bndbox>
	</object>
</annotation>
